{
  "$schema": "../../../schemas/flags.schema.json",
  "kind": "flags",
  "flags": {
    "flag:bridge-fixed": {
      "default": false,
      "description": "Woodcutter has repaired the river bridge at overworld tile [32,28]."
    },
    "flag:castle-armory-seen": {
      "default": false,
      "description": "The player has inspected the old armory standard that names the true dungeon seal."
    },
    "flag:castle-letters-cleared": {
      "default": false,
      "description": "Castle Scribe Elowen has confirmed the library and armory signs point to the dungeon stair."
    },
    "flag:castle-library-read": {
      "default": false,
      "description": "The player has read the castle library archive page about the dungeon seal."
    },
    "flag:has-dungeon-key": {
      "default": false,
      "description": "Player holds the brass dungeon key dropped by the Desert Wyrm; unlocks the castle gate."
    },
    "flag:morning-errands-done": {
      "default": false,
      "description": "Page Pip's morning errand has been carried from the village green to the shop and back."
    },
    "flag:oldwood-oath-sworn": {
      "default": false,
      "description": "The Oldwood Hermit's road oath has been carried past the first forest raiders."
    },
    "flag:ruin-mural-read": {
      "default": false,
      "description": "The player has read Pilgrim Safra's Sunken Road mural inside the desert ruins."
    },
    "flag:lost-page-guided": {
      "default": false,
      "description": "Lost Page Rowan has been guided from the Deep Forest oak back toward the old road."
    },
    "flag:shop-sample-claimed": {
      "default": false,
      "description": "Hearthwake shopkeeper has already given the player the one-time travel cake sample."
    },
    "flag:tavern-song-learned": {
      "default": false,
      "description": "Merrin has explained the hearth-song board's errand verse to the player."
    }
  }
}
